freefang/__init__.py
freefang/example.py
freefang/main.py
freefang/models.py
freefang/net.py
freefang/packets.py
freefang/roles.py
freefang/utils.py
freefang/voting.py
freefang_server-0.4.1.dist-info/LICENSE
freefang_server-0.4.1.dist-info/METADATA
freefang_server-0.4.1.dist-info/WHEEL
freefang_server-0.4.1.dist-info/entry_points.txt
freefang_server-0.4.1.dist-info/top_level.txt
freefang_server-0.4.1.dist-info/RECORD
