Metadata-Version: 2.1
Name: freefang-server
Version: 0.4.1
Summary: The server for FreeFang, a libre python implementation of Werewolf (also known as Mafia)
Author: FreeFang Development Team
Author-email: Solaris <iusegentoobtw@protonmail.com>, lukakralik <luka.kralik@gmail.com>
Project-URL: Homepage, https://github.com/FreeFangGame/freefang-server
Project-URL: Bug Tracker, https://github.com/FreeFangGame/freefang-server/issues
Classifier: Programming Language :: Python :: 3
Classifier: License :: OSI Approved :: GNU Affero General Public License v3
Classifier: Operating System :: OS Independent
License-File: LICENSE
